{
  "credit": "Made with Blockbench",
  "elements": [
    {
      "from": [
        0,
        0,
        15
      ],
      "to": [
        16,
        16,
        15
      ],
      "faces": {
        "north": {
          "uv": [
            0,
            0,
            16,
            16
          ],
          "texture": "#ladder"
        },
        "east": {
          "uv": [
            0,
            0,
            0,
            16
          ],
          "texture": "#ladder"
        },
        "south": {
          "uv": [
            0,
            0,
            16,
            16
          ],
          "texture": "#ladder"
        },
        "west": {
          "uv": [
            0,
            0,
            0,
            16
          ],
          "texture": "#ladder"
        },
        "up": {
          "uv": [
            0,
            0,
            16,
            0
          ],
          "texture": "#ladder"
        },
        "down": {
          "uv": [
            0,
            0,
            16,
            0
          ],
          "texture": "#ladder"
        }
      }
    },
    {
      "from": [
        2,
        16,
        15
      ],
      "to": [
        4,
        17,
        17
      ],
      "faces": {
        "north": {
          "uv": [
            2,
            0,
            4,
            1
          ],
          "texture": "#ladder"
        },
        "east": {
          "uv": [
            0,
            0,
            2,
            1
          ],
          "texture": "#ladder"
        },
        "south": {
          "uv": [
            2,
            1,
            4,
            2
          ],
          "texture": "#ladder"
        },
        "west": {
          "uv": [
            0,
            0,
            2,
            1
          ],
          "texture": "#ladder"
        },
        "up": {
          "uv": [
            2,
            0,
            4,
            2
          ],
          "texture": "#ladder"
        },
        "down": {
          "uv": [
            5,
            3,
            7,
            5
          ],
          "texture": "#ladder"
        }
      }
    },
    {
      "from": [
        12,
        16,
        15
      ],
      "to": [
        14,
        17,
        17
      ],
      "faces": {
        "north": {
          "uv": [
            2,
            0,
            4,
            1
          ],
          "texture": "#ladder"
        },
        "east": {
          "uv": [
            0,
            0,
            2,
            1
          ],
          "texture": "#ladder"
        },
        "south": {
          "uv": [
            2,
            1,
            4,
            2
          ],
          "texture": "#ladder"
        },
        "west": {
          "uv": [
            0,
            0,
            2,
            1
          ],
          "texture": "#ladder"
        },
        "up": {
          "uv": [
            2,
            0,
            4,
            2
          ],
          "texture": "#ladder"
        },
        "down": {
          "uv": [
            5,
            3,
            7,
            5
          ],
          "texture": "#ladder"
        }
      }
    }
  ],
  "display": {
    "thirdperson_righthand": {
      "rotation": [
        75,
        45,
        0
      ],
      "translation": [
        0,
        2.5,
        0
      ],
      "scale": [
        0.375,
        0.375,
        0.375
      ]
    },
    "thirdperson_lefthand": {
      "rotation": [
        75,
        45,
        0
      ],
      "translation": [
        0,
        2.5,
        0
      ],
      "scale": [
        0.375,
        0.375,
        0.375
      ]
    },
    "firstperson_righthand": {
      "rotation": [
        0,
        -90,
        25
      ],
      "translation": [
        1.13,
        3.2,
        1.13
      ],
      "scale": [
        0.68,
        0.68,
        0.68
      ]
    },
    "firstperson_lefthand": {
      "rotation": [
        0,
        -90,
        25
      ],
      "translation": [
        1.13,
        3.2,
        1.13
      ],
      "scale": [
        0.68,
        0.68,
        0.68
      ]
    },
    "gui": {
      "rotation": [
        30,
        225,
        0
      ],
      "translation": [
        3.5,
        -2.25,
        0
      ],
      "scale": [
        0.625,
        0.625,
        0.625
      ]
    },
    "head": {
      "translation": [
        0,
        -1,
        -14.75
      ]
    },
    "fixed": {
      "translation": [
        -0.5,
        0,
        -4.75
      ],
      "scale": [
        0.5,
        0.5,
        0.5
      ]
    }
  },
  "groups": [
    {
      "name": "group",
      "origin": [
        8,
        8,
        8
      ],
      "color": 0,
      "children": [
        0,
        1,
        2
      ]
    }
  ]
}